<?xml version="1.0" encoding="utf-8"?>
<!DOCTYPE hibernate-mapping PUBLIC "-//Hibernate/Hibernate Mapping DTD 3.0//EN"
"http://www.hibernate.org/dtd/hibernate-mapping-3.0.dtd">
<!-- 
    Mapping file autogenerated by MyEclipse Persistence Tools
-->
<hibernate-mapping>
    <class name="com.li.domain.Teacher" table="teacher" catalog="gpms_2014">
        <id name="id" type="java.lang.Integer">
            <column name="id" />
            <generator class="identity" />
        </id>
        <many-to-one name="major" class="com.li.domain.Major" fetch="select">
            <column name="teacher_major_id" not-null="true" />
        </many-to-one>
        <many-to-one name="dept" class="com.li.domain.Dept" fetch="select">
            <column name="teacher_dept_id" not-null="true" />
        </many-to-one>
        <property name="teacherId" type="java.lang.String">
            <column name="teacher_id" length="10" not-null="true" />
        </property>
        <property name="teacherName" type="java.lang.String">
            <column name="teacher_name" length="32" not-null="true" />
        </property>
        <property name="teacherPwd" type="java.lang.String">
            <column name="teacher_pwd" length="16" not-null="true" />
        </property>
        <property name="teacherGrade" type="java.lang.Integer">
            <column name="teacher_grade" not-null="true" />
        </property>
        <property name="teacherTel" type="java.lang.String">
            <column name="teacher_tel" length="16" not-null="true" />
        </property>
        <property name="teacherEmail" type="java.lang.String">
            <column name="teacher_email" length="32" not-null="true" />
        </property>
        <set name="teacherGroups" inverse="true">
            <key>
                <column name="teacher_id" not-null="true" />
            </key>
            <one-to-many class="com.li.domain.TeacherGroup" />
        </set>
        <set name="subjects" inverse="true">
            <key>
                <column name="subject_teacher_id" not-null="true" />
            </key>
            <one-to-many class="com.li.domain.Subject" />
        </set>
        <set name="commentsForCommentMutualTeacher" inverse="true">
            <key>
                <column name="comment_mutual_teacher" />
            </key>
            <one-to-many class="com.li.domain.Comment" />
        </set>
        <set name="commentsForCommentReplyTeacher" inverse="true">
            <key>
                <column name="comment_reply_teacher" />
            </key>
            <one-to-many class="com.li.domain.Comment" />
        </set>
        <set name="commentsForCommentSelfTeacher" inverse="true">
            <key>
                <column name="comment_self_teacher" />
            </key>
            <one-to-many class="com.li.domain.Comment" />
        </set>
    </class>
</hibernate-mapping>
